colabseg/__init__.py
colabseg/image_io.py
colabseg/microscope_db.py
colabseg/napari_integration.py
colabseg/new_gui_functions.py
colabseg/parametrization.py
colabseg/py3dmol_controls.py
colabseg/segmentation_gui.py
colabseg/tensorvoting_wrapper.py
colabseg/test_surface.py
colabseg/utilities.py
tests/__init__.py
tests/test_segmentation_backend.py
tests/test_utilities.py
colabseg-0.0.3.dist-info/LICENSE
colabseg-0.0.3.dist-info/METADATA
colabseg-0.0.3.dist-info/WHEEL
colabseg-0.0.3.dist-info/top_level.txt
colabseg-0.0.3.dist-info/RECORD
