Metadata-Version: 2.1
Name: colabseg
Version: 0.0.3
Summary: Colab Seg 
Author: Marc Siggel
Author-email: marc.siggel@embl-hamburg.de
Keywords: python,first package
Classifier: Development Status :: 3 - Alpha
Classifier: Intended Audience :: Education
Classifier: Programming Language :: Python :: 3
Classifier: Operating System :: MacOS :: MacOS X
Requires-Python: >=3.6, <=3.9
License-File: LICENSE
Requires-Dist: py3Dmol >2.0
Requires-Dist: numpy
Requires-Dist: h5py
Requires-Dist: scipy
Requires-Dist: tqdm
Requires-Dist: matplotlib
Requires-Dist: pandas
Requires-Dist: open3d
Requires-Dist: ipython
Requires-Dist: jupyter
Requires-Dist: future
Requires-Dist: pyntcloud
Requires-Dist: napari
